{
  "group_matched": false,
  "distance_mi": 81,
  "content_hash": "xpOfb1CL1U6EtdruQku9JsRGue2CZOsdQunCv4ixgCvI8",
  "common_friends": [],
  "common_likes": [],
  "common_friend_count": 0,
  "common_like_count": 0,
  "connection_count": 0,
  "_id": "57ea513e597fdffa41f99c98",
  "bio": "",
  "birth_date": "1998-11-28T19:51:59.077Z",
  "name": "Rachelle",
  "ping_time": "2014-12-09T00:00:00.000Z",
  "photos": [
    {
      "id": "debba5e2-5e50-4163-8d3a-8604cedd2b01",
      "crop_info": {
        "user": {
          "width_pct": 1,
          "x_offset_pct": 0,
          "height_pct": 0.8,
          "y_offset_pct": 0
        },
        "algo": {
          "width_pct": 0.2851723518222571,
          "x_offset_pct": 0.4046812784159556,
          "height_pct": 0.2555939461663365,
          "y_offset_pct": 0.1698040907457471
        },
        "processed_by_bullseye": true,
        "user_customized": false
      },
      "url": "https://images-ssl.gotinder.com/57ea513e597fdffa41f99c98/original_debba5e2-5e50-4163-8d3a-8604cedd2b01.jpeg",
      "processedFiles": [
        {
          "url": "https://images-ssl.gotinder.com/57ea513e597fdffa41f99c98/640x800_debba5e2-5e50-4163-8d3a-8604cedd2b01.jpg",
          "height": 800,
          "width": 640
        },
        {
          "url": "https://images-ssl.gotinder.com/57ea513e597fdffa41f99c98/320x400_debba5e2-5e50-4163-8d3a-8604cedd2b01.jpg",
          "height": 400,
          "width": 320
        },
        {
          "url": "https://images-ssl.gotinder.com/57ea513e597fdffa41f99c98/172x216_debba5e2-5e50-4163-8d3a-8604cedd2b01.jpg",
          "height": 216,
          "width": 172
        },
        {
          "url": "https://images-ssl.gotinder.com/57ea513e597fdffa41f99c98/84x106_debba5e2-5e50-4163-8d3a-8604cedd2b01.jpg",
          "height": 106,
          "width": 84
        }
      ],
      "last_update_time": "2019-11-13T07:58:32.171Z",
      "fileName": "debba5e2-5e50-4163-8d3a-8604cedd2b01.webp",
      "extension": "jpg,webp",
      "webp_qf": [
        75
      ]
    },
    {
      "id": "888b41dd-885b-4481-add6-e0e2fa18d2f5",
      "crop_info": {
        "user": {
          "width_pct": 1,
          "x_offset_pct": 0,
          "height_pct": 0.8,
          "y_offset_pct": 0
        },
        "algo": {
          "width_pct": 0.16078399582766,
          "x_offset_pct": 0.27378815985284743,
          "height_pct": 0.18719128618948164,
          "y_offset_pct": 0.08492377368733287
        },
        "processed_by_bullseye": true,
        "user_customized": false
      },
      "url": "https://images-ssl.gotinder.com/57ea513e597fdffa41f99c98/original_888b41dd-885b-4481-add6-e0e2fa18d2f5.jpeg",
      "processedFiles": [
        {
          "url": "https://images-ssl.gotinder.com/57ea513e597fdffa41f99c98/640x800_888b41dd-885b-4481-add6-e0e2fa18d2f5.jpg",
          "height": 800,
          "width": 640
        },
        {
          "url": "https://images-ssl.gotinder.com/57ea513e597fdffa41f99c98/320x400_888b41dd-885b-4481-add6-e0e2fa18d2f5.jpg",
          "height": 400,
          "width": 320
        },
        {
          "url": "https://images-ssl.gotinder.com/57ea513e597fdffa41f99c98/172x216_888b41dd-885b-4481-add6-e0e2fa18d2f5.jpg",
          "height": 216,
          "width": 172
        },
        {
          "url": "https://images-ssl.gotinder.com/57ea513e597fdffa41f99c98/84x106_888b41dd-885b-4481-add6-e0e2fa18d2f5.jpg",
          "height": 106,
          "width": 84
        }
      ],
      "last_update_time": "2019-11-09T18:45:29.215Z",
      "fileName": "888b41dd-885b-4481-add6-e0e2fa18d2f5.webp",
      "extension": "jpg,webp",
      "webp_qf": [
        75
      ]
    },
    {
      "id": "20e59ffe-395f-46d6-b71e-527b37266710",
      "crop_info": {
        "user": {
          "width_pct": 1,
          "x_offset_pct": 0,
          "height_pct": 0.8,
          "y_offset_pct": 0.032914547419641144
        },
        "algo": {
          "width_pct": 0.421732820617035,
          "x_offset_pct": 0.3485923632979393,
          "height_pct": 0.4264486086787656,
          "y_offset_pct": 0.21969024308025836
        },
        "processed_by_bullseye": true,
        "user_customized": false
      },
      "url": "https://images-ssl.gotinder.com/57ea513e597fdffa41f99c98/original_20e59ffe-395f-46d6-b71e-527b37266710.jpeg",
      "processedFiles": [
        {
          "url": "https://images-ssl.gotinder.com/57ea513e597fdffa41f99c98/640x800_20e59ffe-395f-46d6-b71e-527b37266710.jpg",
          "height": 800,
          "width": 640
        },
        {
          "url": "https://images-ssl.gotinder.com/57ea513e597fdffa41f99c98/320x400_20e59ffe-395f-46d6-b71e-527b37266710.jpg",
          "height": 400,
          "width": 320
        },
        {
          "url": "https://images-ssl.gotinder.com/57ea513e597fdffa41f99c98/172x216_20e59ffe-395f-46d6-b71e-527b37266710.jpg",
          "height": 216,
          "width": 172
        },
        {
          "url": "https://images-ssl.gotinder.com/57ea513e597fdffa41f99c98/84x106_20e59ffe-395f-46d6-b71e-527b37266710.jpg",
          "height": 106,
          "width": 84
        }
      ],
      "last_update_time": "2019-09-03T11:26:17.233Z",
      "fileName": "20e59ffe-395f-46d6-b71e-527b37266710.webp",
      "extension": "jpg,webp",
      "webp_qf": [
        75
      ]
    }
  ],
  "instagram": {
    "last_fetch_time": "2019-11-25T18:35:00.040Z",
    "completed_initial_fetch": true,
    "photos": [
      {
        "image": "https://scontent.cdninstagram.com/v/t51.2885-15/sh0.08/e35/s640x640/73381142_579833592557996_2402944671081408124_n.jpg?_nc_ht=scontent.cdninstagram.com&oh=a043340181c36b403b1d38b06a03b4fe&oe=5E696219",
        "thumbnail": "https://scontent.cdninstagram.com/v/t51.2885-15/e35/s150x150/73381142_579833592557996_2402944671081408124_n.jpg?_nc_ht=scontent.cdninstagram.com&oh=0fa7bdb3c6493f86421e2673279f1bc9&oe=5E7C78BE",
        "ts": "1574615509"
      },
      {
        "image": "https://scontent.cdninstagram.com/v/t51.2885-15/sh0.08/e35/s640x640/72286300_555636201650305_7106644391260424328_n.jpg?_nc_ht=scontent.cdninstagram.com&oh=1366e48e705016bcc6fc699dbcde513e&oe=5E762BFB",
        "thumbnail": "https://scontent.cdninstagram.com/v/t51.2885-15/e35/s150x150/72286300_555636201650305_7106644391260424328_n.jpg?_nc_ht=scontent.cdninstagram.com&oh=cbdaeffe4ce55814e3d5a9ccd9202328&oe=5E83A75C",
        "ts": "1574107109"
      },
      {
        "image": "https://scontent.cdninstagram.com/v/t51.2885-15/sh0.08/e35/p640x640/71312154_155284442513051_1742387257978344816_n.jpg?_nc_ht=scontent.cdninstagram.com&oh=f60914d4336212c4235f948c91714d06&oe=5E6A5825",
        "thumbnail": "https://scontent.cdninstagram.com/v/t51.2885-15/e35/c0.70.1440.1440a/s150x150/71312154_155284442513051_1742387257978344816_n.jpg?_nc_ht=scontent.cdninstagram.com&oh=00a62bc20dff9fc9af98917c4ddab796&oe=5E7E0793",
        "ts": "1574008704"
      },
      {
        "image": "https://scontent.cdninstagram.com/v/t51.2885-15/sh0.08/e35/p640x640/71546359_683897888799172_5637043120655306260_n.jpg?_nc_ht=scontent.cdninstagram.com&oh=35b8b225b13e44c6461e5ae296131ee0&oe=5E7492EA",
        "thumbnail": "https://scontent.cdninstagram.com/v/t51.2885-15/e35/c0.47.1440.1440a/s150x150/71546359_683897888799172_5637043120655306260_n.jpg?_nc_ht=scontent.cdninstagram.com&oh=6b7ef7d89e680afdccf2e2b96954497d&oe=5E695761",
        "ts": "1572019056"
      },
      {
        "image": "https://scontent.cdninstagram.com/v/t51.2885-15/sh0.08/e35/p640x640/71895774_2352190694998367_6482196918908156476_n.jpg?_nc_ht=scontent.cdninstagram.com&oh=9b83a57438af6ca93b595230df721b5f&oe=5E7F009B",
        "thumbnail": "https://scontent.cdninstagram.com/v/t51.2885-15/e35/c0.48.1440.1440a/s150x150/71895774_2352190694998367_6482196918908156476_n.jpg?_nc_ht=scontent.cdninstagram.com&oh=18a0b54ec5b6e07c64bdea3d50990c73&oe=5E7863CB",
        "ts": "1571417522"
      },
      {
        "image": "https://scontent.cdninstagram.com/v/t51.2885-15/sh0.08/e35/s640x640/71120009_166723427772527_4553870399661084245_n.jpg?_nc_ht=scontent.cdninstagram.com&oh=cbde29759cc50e5ea1abd03faf854a12&oe=5E8BBA16",
        "thumbnail": "https://scontent.cdninstagram.com/v/t51.2885-15/e35/s150x150/71120009_166723427772527_4553870399661084245_n.jpg?_nc_ht=scontent.cdninstagram.com&oh=de25c3d45a5c83c0a7d5cfd434dbed58&oe=5E837EB1",
        "ts": "1571241112"
      },
      {
        "image": "https://scontent.cdninstagram.com/v/t51.2885-15/sh0.08/e35/s640x640/70697834_186576202383827_2680474298979392873_n.jpg?_nc_ht=scontent.cdninstagram.com&oh=7d2fd153dda95552b483e323607bf86e&oe=5E661B84",
        "thumbnail": "https://scontent.cdninstagram.com/v/t51.2885-15/e35/s150x150/70697834_186576202383827_2680474298979392873_n.jpg?_nc_ht=scontent.cdninstagram.com&oh=cb9366a75447126c64183ad0df62107d&oe=5E766423",
        "ts": "1571071694"
      },
      {
        "image": "https://scontent.cdninstagram.com/v/t51.2885-15/sh0.08/e35/s640x640/70504130_212909396366214_1450172619501499300_n.jpg?_nc_ht=scontent.cdninstagram.com&oh=9748b8204ef24d67fedc7a413cfbb34d&oe=5E7ACA87",
        "thumbnail": "https://scontent.cdninstagram.com/v/t51.2885-15/e35/s150x150/70504130_212909396366214_1450172619501499300_n.jpg?_nc_ht=scontent.cdninstagram.com&oh=0c468aec674b03bb00634285fd027a6e&oe=5E8AC120",
        "ts": "1569945900"
      },
      {
        "image": "https://scontent.cdninstagram.com/v/t51.2885-15/sh0.08/e35/p640x640/70357313_534068197349625_2621260360394445978_n.jpg?_nc_ht=scontent.cdninstagram.com&oh=e353ba8d612168a88fb294e8dbe639b3&oe=5E6EBC66",
        "thumbnail": "https://scontent.cdninstagram.com/v/t51.2885-15/e35/c0.155.1440.1440a/s150x150/70357313_534068197349625_2621260360394445978_n.jpg?_nc_ht=scontent.cdninstagram.com&oh=b921194d7b4b1a6cc867f247884221e1&oe=5E879B1C",
        "ts": "1569859628"
      },
      {
        "image": "https://scontent.cdninstagram.com/v/t51.2885-15/sh0.08/e35/s640x640/70695471_742236742884583_2210062446837926041_n.jpg?_nc_ht=scontent.cdninstagram.com&oh=50f7e2ab5e6246cfcc37fd275b5d7284&oe=5E893E6B",
        "thumbnail": "https://scontent.cdninstagram.com/v/t51.2885-15/e35/s150x150/70695471_742236742884583_2210062446837926041_n.jpg?_nc_ht=scontent.cdninstagram.com&oh=bd423f9d437b2fba8d39685d2638c397&oe=5E7674CC",
        "ts": "1569340814"
      },
      {
        "image": "https://scontent.cdninstagram.com/v/t51.2885-15/sh0.08/e35/p640x640/70012037_411162449542854_5790379162082604567_n.jpg?_nc_ht=scontent.cdninstagram.com&oh=b2b473d44b09c07edfd6474c649fc666&oe=5E66B49A",
        "thumbnail": "https://scontent.cdninstagram.com/v/t51.2885-15/e35/c0.179.1440.1440a/s150x150/70012037_411162449542854_5790379162082604567_n.jpg?_nc_ht=scontent.cdninstagram.com&oh=e27b655b2780e7ea2d5e8424da2708ab&oe=5E691049",
        "ts": "1569169418"
      },
      {
        "image": "https://scontent.cdninstagram.com/v/t51.2885-15/sh0.08/e35/s640x640/69287786_1309908319170979_8313129840790453930_n.jpg?_nc_ht=scontent.cdninstagram.com&oh=dfa0ac72dd00245e1680646f595e612e&oe=5E713F59",
        "thumbnail": "https://scontent.cdninstagram.com/v/t51.2885-15/e35/s150x150/69287786_1309908319170979_8313129840790453930_n.jpg?_nc_ht=scontent.cdninstagram.com&oh=932bf1ed3a9f4d439311946b5223a49e&oe=5E7BC7DC",
        "ts": "1568909100"
      },
      {
        "image": "https://scontent.cdninstagram.com/v/t51.2885-15/sh0.08/e35/s640x640/67776777_382047432727770_733665298192332767_n.jpg?_nc_ht=scontent.cdninstagram.com&oh=52c5368086465aa8e7c7805ab8fd81a9&oe=5E78E6D9",
        "thumbnail": "https://scontent.cdninstagram.com/v/t51.2885-15/e35/s150x150/67776777_382047432727770_733665298192332767_n.jpg?_nc_ht=scontent.cdninstagram.com&oh=449fc5d9c89f179dfc788ba60a799a7b&oe=5E698A38",
        "ts": "1568461904"
      },
      {
        "image": "https://scontent.cdninstagram.com/v/t51.2885-15/sh0.08/e35/s640x640/69470440_738076526641975_4878733091123201535_n.jpg?_nc_ht=scontent.cdninstagram.com&oh=a04b3ae53aa3816b52b528e14b9ec6e1&oe=5E80AEAB",
        "thumbnail": "https://scontent.cdninstagram.com/v/t51.2885-15/e35/s150x150/69470440_738076526641975_4878733091123201535_n.jpg?_nc_ht=scontent.cdninstagram.com&oh=97ebb6ef2d20dbcf14a6c9d0fe309b88&oe=5E73950C",
        "ts": "1568390427"
      },
      {
        "image": "https://scontent.cdninstagram.com/v/t51.2885-15/sh0.08/e35/p640x640/70445645_166765931115867_3384959572828017153_n.jpg?_nc_ht=scontent.cdninstagram.com&oh=e66934a086f98cc2db29f32264cf4b47&oe=5E80FA04",
        "thumbnail": "https://scontent.cdninstagram.com/v/t51.2885-15/e35/c0.26.1440.1440a/s150x150/70445645_166765931115867_3384959572828017153_n.jpg?_nc_ht=scontent.cdninstagram.com&oh=2ed5dfac127653645adae5ffebd73408&oe=5E6B80FC",
        "ts": "1568304023"
      },
      {
        "image": "https://scontent.cdninstagram.com/v/t51.2885-15/sh0.08/e35/s640x640/69774632_373382790262080_2563401235077368096_n.jpg?_nc_ht=scontent.cdninstagram.com&oh=0cde68cb284a160044a40908a4e2fade&oe=5E69F65C",
        "thumbnail": "https://scontent.cdninstagram.com/v/t51.2885-15/e35/s150x150/69774632_373382790262080_2563401235077368096_n.jpg?_nc_ht=scontent.cdninstagram.com&oh=bfd4df138f4add2449bb75b6b706cd8b&oe=5E6ADCFB",
        "ts": "1568131218"
      },
      {
        "image": "https://scontent.cdninstagram.com/v/t51.2885-15/sh0.08/e35/s640x640/70199660_2150380781922066_1449639584939853973_n.jpg?_nc_ht=scontent.cdninstagram.com&oh=893c30ea15a298cb67c42139036954e7&oe=5E7C98C3",
        "thumbnail": "https://scontent.cdninstagram.com/v/t51.2885-15/e35/s150x150/70199660_2150380781922066_1449639584939853973_n.jpg?_nc_ht=scontent.cdninstagram.com&oh=c9f5de09d2693efe441cd341dc40c038&oe=5E7B4946",
        "ts": "1567959208"
      },
      {
        "image": "https://scontent.cdninstagram.com/v/t51.2885-15/sh0.08/e35/p640x640/68908792_155992885477778_1489421294429892407_n.jpg?_nc_ht=scontent.cdninstagram.com&oh=372d588d799ee50cb5badaa7d1c539b1&oe=5E7496CB",
        "thumbnail": "https://scontent.cdninstagram.com/v/t51.2885-15/e35/c0.93.1440.1440a/s150x150/68908792_155992885477778_1489421294429892407_n.jpg?_nc_ht=scontent.cdninstagram.com&oh=54b5962b8bee4f60c926e92b0f2b3ce9&oe=5E701E13",
        "ts": "1567787676"
      },
      {
        "image": "https://scontent.cdninstagram.com/v/t51.2885-15/sh0.08/e35/p640x640/68941876_1450841575069978_2164534938370781702_n.jpg?_nc_ht=scontent.cdninstagram.com&oh=913c8bb36f9eacc8b2e2c910917b895e&oe=5E7D3CFB",
        "thumbnail": "https://scontent.cdninstagram.com/v/t51.2885-15/e35/c0.64.1440.1440a/s150x150/68941876_1450841575069978_2164534938370781702_n.jpg?_nc_ht=scontent.cdninstagram.com&oh=f6b3d1cb43094fbebb5a3f2ae99953f6&oe=5E6BAE92",
        "ts": "1567612783"
      },
      {
        "image": "https://scontent.cdninstagram.com/v/t51.2885-15/sh0.08/e35/s640x640/67848039_371720103507461_4655514689258767126_n.jpg?_nc_ht=scontent.cdninstagram.com&oh=076841f7a8f5bd141ba574b68dbf94a7&oe=5E8CDF4F",
        "thumbnail": "https://scontent.cdninstagram.com/v/t51.2885-15/e35/s150x150/67848039_371720103507461_4655514689258767126_n.jpg?_nc_ht=scontent.cdninstagram.com&oh=4a35a0d7be0afd614b8d07143ed79d8d&oe=5E7331E8",
        "ts": "1567529623"
      },
      {
        "image": "https://scontent.cdninstagram.com/v/t51.2885-15/sh0.08/e35/s640x640/70844473_158388741975806_1542103614070125746_n.jpg?_nc_ht=scontent.cdninstagram.com&oh=77363f92a334592bb7301c7987a0e98c&oe=5E86F599",
        "thumbnail": "https://scontent.cdninstagram.com/v/t51.2885-15/e35/s150x150/70844473_158388741975806_1542103614070125746_n.jpg?_nc_ht=scontent.cdninstagram.com&oh=48f6a4f016d317945a7bff81c7a3f0e4&oe=5E8A253E",
        "ts": "1567438179"
      },
      {
        "image": "https://scontent.cdninstagram.com/v/t51.2885-15/sh0.08/e35/s640x640/67778183_2670412972977769_6966467311786473980_n.jpg?_nc_ht=scontent.cdninstagram.com&oh=8fa91b9ff16c6747d93adc6a3fbce5dc&oe=5E8C2E82",
        "thumbnail": "https://scontent.cdninstagram.com/v/t51.2885-15/e35/s150x150/67778183_2670412972977769_6966467311786473980_n.jpg?_nc_ht=scontent.cdninstagram.com&oh=f76149e2c624da4d6ea4d6d27cec8272&oe=5E6FCE07",
        "ts": "1567354436"
      },
      {
        "image": "https://scontent.cdninstagram.com/v/t51.2885-15/sh0.08/e35/s640x640/67547256_155789535513581_3108929911139216366_n.jpg?_nc_ht=scontent.cdninstagram.com&oh=d50cbfad2e364b88ed0cb86e236606fe&oe=5E8A86FD",
        "thumbnail": "https://scontent.cdninstagram.com/v/t51.2885-15/e35/s150x150/67547256_155789535513581_3108929911139216366_n.jpg?_nc_ht=scontent.cdninstagram.com&oh=fb17aa61f3f0f1be243546d3eadd75f3&oe=5E8C8C5A",
        "ts": "1567267365"
      },
      {
        "image": "https://scontent.cdninstagram.com/v/t51.2885-15/sh0.08/e35/p640x640/67944120_537071383703433_5746708197191391096_n.jpg?_nc_ht=scontent.cdninstagram.com&oh=e38c21f7e49dd24f64d7a3793910576f&oe=5E77E9E9",
        "thumbnail": "https://scontent.cdninstagram.com/v/t51.2885-15/e35/c0.180.1440.1440a/s150x150/67944120_537071383703433_5746708197191391096_n.jpg?_nc_ht=scontent.cdninstagram.com&oh=dea2d148f0aae14b50483c2f570ff8f9&oe=5E6CB954",
        "ts": "1567180545"
      },
      {
        "image": "https://scontent.cdninstagram.com/v/t51.2885-15/sh0.08/e35/s640x640/68826892_185681139116542_1823603920602013197_n.jpg?_nc_ht=scontent.cdninstagram.com&oh=837c6d8a860fdf8fcaca30392d6bc242&oe=5E85085B",
        "thumbnail": "https://scontent.cdninstagram.com/v/t51.2885-15/e35/s150x150/68826892_185681139116542_1823603920602013197_n.jpg?_nc_ht=scontent.cdninstagram.com&oh=a51bdedfafffa49ecf21ae1577d336c5&oe=5E889DFC",
        "ts": "1567003719"
      },
      {
        "image": "https://scontent.cdninstagram.com/v/t51.2885-15/sh0.08/e35/s640x640/67402812_976756642678956_8745525091544397859_n.jpg?_nc_ht=scontent.cdninstagram.com&oh=dbc686295a9d41e502bb46a5e4009b99&oe=5E868AC6",
        "thumbnail": "https://scontent.cdninstagram.com/v/t51.2885-15/e35/s150x150/67402812_976756642678956_8745525091544397859_n.jpg?_nc_ht=scontent.cdninstagram.com&oh=ef9106e346ef16b3ae36a101dffeeee7&oe=5E75F361",
        "ts": "1566834808"
      },
      {
        "image": "https://scontent.cdninstagram.com/v/t51.2885-15/sh0.08/e35/p640x640/67615272_711718619256139_1801973146757023706_n.jpg?_nc_ht=scontent.cdninstagram.com&oh=2b0e30dc30a183d81f7f8b89cc24c2d9&oe=5E794F8C",
        "thumbnail": "https://scontent.cdninstagram.com/v/t51.2885-15/e35/c0.180.1440.1440a/s150x150/67615272_711718619256139_1801973146757023706_n.jpg?_nc_ht=scontent.cdninstagram.com&oh=614764d56aa3c4ca6979c3c3888db5a3&oe=5E681731",
        "ts": "1566662398"
      },
      {
        "image": "https://scontent.cdninstagram.com/v/t51.2885-15/sh0.08/e35/s640x640/67620466_967707263622561_6586678049497897721_n.jpg?_nc_ht=scontent.cdninstagram.com&oh=2def9a24164726f1a296ca11e5c1586e&oe=5E76835C",
        "thumbnail": "https://scontent.cdninstagram.com/v/t51.2885-15/e35/s150x150/67620466_967707263622561_6586678049497897721_n.jpg?_nc_ht=scontent.cdninstagram.com&oh=9de7eda5afadcf8d844f8c9f48fc0688&oe=5E75B7FB",
        "ts": "1566132382"
      },
      {
        "image": "https://scontent.cdninstagram.com/v/t51.2885-15/sh0.08/e35/s640x640/66718899_124201208892788_8013505901673932011_n.jpg?_nc_ht=scontent.cdninstagram.com&oh=645652db6b61f718a25583628e5f43c8&oe=5E756F7D",
        "thumbnail": "https://scontent.cdninstagram.com/v/t51.2885-15/e35/s150x150/66718899_124201208892788_8013505901673932011_n.jpg?_nc_ht=scontent.cdninstagram.com&oh=5cc11ad10b828e718c5338f9a118b132&oe=5E6C6FDA",
        "ts": "1565888506"
      },
      {
        "image": "https://scontent.cdninstagram.com/v/t51.2885-15/sh0.08/e35/s640x640/67410282_155401895639265_5404357157735785054_n.jpg?_nc_ht=scontent.cdninstagram.com&oh=ef25930832ab3f4e9badaee1913291a1&oe=5E84FACF",
        "thumbnail": "https://scontent.cdninstagram.com/v/t51.2885-15/e35/s150x150/67410282_155401895639265_5404357157735785054_n.jpg?_nc_ht=scontent.cdninstagram.com&oh=b270f3ef09c06f49ad03bd84fd934956&oe=5E807368",
        "ts": "1565539432"
      }
    ],
    "media_count": 71,
    "profile_picture": "https://scontent.cdninstagram.com/vp/b0660d4de6c557b3dc7f8dde32382747/5E72D97B/t51.2885-19/s150x150/71577603_769751453474013_288124561042440192_n.jpg?_nc_ht=scontent.cdninstagram.com",
    "username": "Tinder"
  },
  "jobs": [],
  "schools": [
    {
      "name": "Kapster"
    }
  ],
  "teaser": {
    "type": "school",
    "string": "Kapster"
  },
  "teasers": [
    {
      "type": "school",
      "string": "Kapster"
    },
    {
      "type": "instagram",
      "string": "71 Instagram Photos"
    }
  ],
  "gender": 1,
  "birth_date_info": "fuzzy birthdate active, not displaying real birth_date",
  "s_number": 263956632
}