{
  "group_matched": false,
  "distance_mi": 76,
  "content_hash": "Z5F6ph2aHmwtM1T1XF9nIPGT6xuLqCqjfZ6U92uDPtDbi9P",
  "common_friends": [],
  "common_likes": [],
  "common_friend_count": 0,
  "common_like_count": 0,
  "connection_count": 0,
  "_id": "587b84f9c89e01295f0c4a2d",
  "bio": "",
  "birth_date": "1989-11-25T20:11:41.528Z",
  "name": "Elodie",
  "ping_time": "2014-12-09T00:00:00.000Z",
  "photos": [
    {
      "id": "1137327d-fa47-4edf-b04a-36ef6b5eb894",
      "crop_info": {
        "user": {
          "width_pct": 1,
          "x_offset_pct": 0,
          "height_pct": 0.8,
          "y_offset_pct": 0
        },
        "algo": {
          "width_pct": 0.4986139432934579,
          "x_offset_pct": 0.23277235215064138,
          "height_pct": 0.47117468882352115,
          "y_offset_pct": 0
        },
        "processed_by_bullseye": true,
        "user_customized": false
      },
      "url": "https://images-ssl.gotinder.com/587b84f9c89e01295f0c4a2d/original_1137327d-fa47-4edf-b04a-36ef6b5eb894.jpeg",
      "processedFiles": [
        {
          "url": "https://images-ssl.gotinder.com/587b84f9c89e01295f0c4a2d/640x800_1137327d-fa47-4edf-b04a-36ef6b5eb894.jpg",
          "height": 800,
          "width": 640
        },
        {
          "url": "https://images-ssl.gotinder.com/587b84f9c89e01295f0c4a2d/320x400_1137327d-fa47-4edf-b04a-36ef6b5eb894.jpg",
          "height": 400,
          "width": 320
        },
        {
          "url": "https://images-ssl.gotinder.com/587b84f9c89e01295f0c4a2d/172x216_1137327d-fa47-4edf-b04a-36ef6b5eb894.jpg",
          "height": 216,
          "width": 172
        },
        {
          "url": "https://images-ssl.gotinder.com/587b84f9c89e01295f0c4a2d/84x106_1137327d-fa47-4edf-b04a-36ef6b5eb894.jpg",
          "height": 106,
          "width": 84
        }
      ],
      "last_update_time": "2019-09-02T14:02:13.255Z",
      "fileName": "1137327d-fa47-4edf-b04a-36ef6b5eb894.webp",
      "extension": "jpg,webp",
      "webp_qf": [
        75
      ]
    },
    {
      "id": "93674328-bf1c-46c0-b3c2-5e157d4e3d0a",
      "crop_info": {
        "user": {
          "width_pct": 1,
          "x_offset_pct": 0,
          "height_pct": 1,
          "y_offset_pct": 0
        },
        "algo": {
          "width_pct": 0.3307151144545059,
          "x_offset_pct": 0.30367236452293583,
          "height_pct": 0.34270083502051424,
          "y_offset_pct": 0.1591624939290341
        },
        "processed_by_bullseye": true,
        "user_customized": false
      },
      "url": "https://images-ssl.gotinder.com/587b84f9c89e01295f0c4a2d/original_93674328-bf1c-46c0-b3c2-5e157d4e3d0a.jpeg",
      "processedFiles": [
        {
          "url": "https://images-ssl.gotinder.com/587b84f9c89e01295f0c4a2d/640x640_93674328-bf1c-46c0-b3c2-5e157d4e3d0a.jpg",
          "height": 640,
          "width": 640
        },
        {
          "url": "https://images-ssl.gotinder.com/587b84f9c89e01295f0c4a2d/320x320_93674328-bf1c-46c0-b3c2-5e157d4e3d0a.jpg",
          "height": 320,
          "width": 320
        },
        {
          "url": "https://images-ssl.gotinder.com/587b84f9c89e01295f0c4a2d/172x172_93674328-bf1c-46c0-b3c2-5e157d4e3d0a.jpg",
          "height": 172,
          "width": 172
        },
        {
          "url": "https://images-ssl.gotinder.com/587b84f9c89e01295f0c4a2d/84x84_93674328-bf1c-46c0-b3c2-5e157d4e3d0a.jpg",
          "height": 84,
          "width": 84
        }
      ],
      "last_update_time": "2019-08-31T16:18:08.387Z",
      "fileName": "93674328-bf1c-46c0-b3c2-5e157d4e3d0a.webp",
      "extension": "jpg,webp",
      "xoffset_percent": 0.12970711290836334,
      "yoffset_percent": 0.03055555559694767,
      "xdistance_percent": 0.7991631627082825,
      "ydistance_percent": 0.7958333492279053,
      "webp_qf": [
        75
      ]
    },
    {
      "id": "a9f50c6c-405a-498e-ba1a-500ceb12db08",
      "crop_info": {
        "user": {
          "width_pct": 1,
          "x_offset_pct": 0,
          "height_pct": 0.8,
          "y_offset_pct": 0
        },
        "algo": {
          "width_pct": 0.09785773085895921,
          "x_offset_pct": 0.6448919435497373,
          "height_pct": 0.09490425871219485,
          "y_offset_pct": 0.22199232548009604
        },
        "processed_by_bullseye": true,
        "user_customized": false
      },
      "url": "https://images-ssl.gotinder.com/587b84f9c89e01295f0c4a2d/original_a9f50c6c-405a-498e-ba1a-500ceb12db08.jpeg",
      "processedFiles": [
        {
          "url": "https://images-ssl.gotinder.com/587b84f9c89e01295f0c4a2d/640x800_a9f50c6c-405a-498e-ba1a-500ceb12db08.jpg",
          "height": 800,
          "width": 640
        },
        {
          "url": "https://images-ssl.gotinder.com/587b84f9c89e01295f0c4a2d/320x400_a9f50c6c-405a-498e-ba1a-500ceb12db08.jpg",
          "height": 400,
          "width": 320
        },
        {
          "url": "https://images-ssl.gotinder.com/587b84f9c89e01295f0c4a2d/172x216_a9f50c6c-405a-498e-ba1a-500ceb12db08.jpg",
          "height": 216,
          "width": 172
        },
        {
          "url": "https://images-ssl.gotinder.com/587b84f9c89e01295f0c4a2d/84x106_a9f50c6c-405a-498e-ba1a-500ceb12db08.jpg",
          "height": 106,
          "width": 84
        }
      ],
      "last_update_time": "2019-08-31T16:15:43.533Z",
      "fileName": "a9f50c6c-405a-498e-ba1a-500ceb12db08.webp",
      "extension": "jpg,webp",
      "webp_qf": [
        75
      ]
    },
    {
      "id": "423af710-aa00-496a-89c8-5a1027fa6145",
      "crop_info": {
        "user": {
          "width_pct": 1,
          "x_offset_pct": 0,
          "height_pct": 0.8,
          "y_offset_pct": 0.09495491385459898
        },
        "algo": {
          "width_pct": 0.9524917602539062,
          "x_offset_pct": 0,
          "height_pct": 0.8323217630386353,
          "y_offset_pct": 0.07879403233528137
        },
        "processed_by_bullseye": true,
        "user_customized": false
      },
      "url": "https://images-ssl.gotinder.com/587b84f9c89e01295f0c4a2d/1080x1350_129d0846-6352-4b27-a247-f0da0a8c6736.jpg",
      "processedFiles": [
        {
          "url": "https://images-ssl.gotinder.com/587b84f9c89e01295f0c4a2d/640x800_129d0846-6352-4b27-a247-f0da0a8c6736.jpg",
          "height": 800,
          "width": 640
        },
        {
          "url": "https://images-ssl.gotinder.com/587b84f9c89e01295f0c4a2d/320x400_129d0846-6352-4b27-a247-f0da0a8c6736.jpg",
          "height": 400,
          "width": 320
        },
        {
          "url": "https://images-ssl.gotinder.com/587b84f9c89e01295f0c4a2d/172x216_129d0846-6352-4b27-a247-f0da0a8c6736.jpg",
          "height": 216,
          "width": 172
        },
        {
          "url": "https://images-ssl.gotinder.com/587b84f9c89e01295f0c4a2d/84x106_129d0846-6352-4b27-a247-f0da0a8c6736.jpg",
          "height": 106,
          "width": 84
        }
      ],
      "fileName": "129d0846-6352-4b27-a247-f0da0a8c6736.jpg",
      "extension": "jpg"
    },
    {
      "id": "91493b44-98d2-4bf5-a17f-f0bdb7367a90",
      "crop_info": {
        "user": {
          "width_pct": 1,
          "x_offset_pct": 0,
          "height_pct": 0.8,
          "y_offset_pct": 0
        },
        "algo": {
          "width_pct": 0.5250291145872324,
          "x_offset_pct": 0,
          "height_pct": 0.4424277049489319,
          "y_offset_pct": 0
        },
        "processed_by_bullseye": true,
        "user_customized": false
      },
      "url": "https://images-ssl.gotinder.com/587b84f9c89e01295f0c4a2d/original_91493b44-98d2-4bf5-a17f-f0bdb7367a90.jpeg",
      "processedFiles": [
        {
          "url": "https://images-ssl.gotinder.com/587b84f9c89e01295f0c4a2d/640x800_91493b44-98d2-4bf5-a17f-f0bdb7367a90.jpg",
          "height": 800,
          "width": 640
        },
        {
          "url": "https://images-ssl.gotinder.com/587b84f9c89e01295f0c4a2d/320x400_91493b44-98d2-4bf5-a17f-f0bdb7367a90.jpg",
          "height": 400,
          "width": 320
        },
        {
          "url": "https://images-ssl.gotinder.com/587b84f9c89e01295f0c4a2d/172x216_91493b44-98d2-4bf5-a17f-f0bdb7367a90.jpg",
          "height": 216,
          "width": 172
        },
        {
          "url": "https://images-ssl.gotinder.com/587b84f9c89e01295f0c4a2d/84x106_91493b44-98d2-4bf5-a17f-f0bdb7367a90.jpg",
          "height": 106,
          "width": 84
        }
      ],
      "last_update_time": "2019-08-31T16:16:20.481Z",
      "fileName": "91493b44-98d2-4bf5-a17f-f0bdb7367a90.webp",
      "extension": "jpg,webp",
      "webp_qf": [
        75
      ]
    },
    {
      "id": "3c50afec-7640-4b18-827b-ee5e6b98247f",
      "crop_info": {
        "processed_by_bullseye": true,
        "user_customized": false
      },
      "url": "https://images-ssl.gotinder.com/587b84f9c89e01295f0c4a2d/1080x1350_3c50afec-7640-4b18-827b-ee5e6b98247f.jpg",
      "processedFiles": [
        {
          "url": "https://images-ssl.gotinder.com/587b84f9c89e01295f0c4a2d/640x800_3c50afec-7640-4b18-827b-ee5e6b98247f.jpg",
          "height": 800,
          "width": 640
        },
        {
          "url": "https://images-ssl.gotinder.com/587b84f9c89e01295f0c4a2d/320x400_3c50afec-7640-4b18-827b-ee5e6b98247f.jpg",
          "height": 400,
          "width": 320
        },
        {
          "url": "https://images-ssl.gotinder.com/587b84f9c89e01295f0c4a2d/172x216_3c50afec-7640-4b18-827b-ee5e6b98247f.jpg",
          "height": 216,
          "width": 172
        },
        {
          "url": "https://images-ssl.gotinder.com/587b84f9c89e01295f0c4a2d/84x106_3c50afec-7640-4b18-827b-ee5e6b98247f.jpg",
          "height": 106,
          "width": 84
        }
      ],
      "fileName": "3c50afec-7640-4b18-827b-ee5e6b98247f.jpg",
      "extension": "jpg"
    },
    {
      "id": "42d2e7fe-04e3-492e-9237-287325db4d1b",
      "crop_info": {
        "user": {
          "width_pct": 1,
          "x_offset_pct": 0,
          "height_pct": 0.8,
          "y_offset_pct": 0
        },
        "algo": {
          "width_pct": 0.3967683880124242,
          "x_offset_pct": 0.5274968261830508,
          "height_pct": 0.44156160920858384,
          "y_offset_pct": 0.006076239794492721
        },
        "processed_by_bullseye": true,
        "user_customized": false
      },
      "url": "https://images-ssl.gotinder.com/587b84f9c89e01295f0c4a2d/original_42d2e7fe-04e3-492e-9237-287325db4d1b.jpeg",
      "processedFiles": [
        {
          "url": "https://images-ssl.gotinder.com/587b84f9c89e01295f0c4a2d/640x800_42d2e7fe-04e3-492e-9237-287325db4d1b.jpg",
          "height": 800,
          "width": 640
        },
        {
          "url": "https://images-ssl.gotinder.com/587b84f9c89e01295f0c4a2d/320x400_42d2e7fe-04e3-492e-9237-287325db4d1b.jpg",
          "height": 400,
          "width": 320
        },
        {
          "url": "https://images-ssl.gotinder.com/587b84f9c89e01295f0c4a2d/172x216_42d2e7fe-04e3-492e-9237-287325db4d1b.jpg",
          "height": 216,
          "width": 172
        },
        {
          "url": "https://images-ssl.gotinder.com/587b84f9c89e01295f0c4a2d/84x106_42d2e7fe-04e3-492e-9237-287325db4d1b.jpg",
          "height": 106,
          "width": 84
        }
      ],
      "last_update_time": "2019-11-19T20:42:08.531Z",
      "fileName": "42d2e7fe-04e3-492e-9237-287325db4d1b.webp",
      "extension": "jpg,webp",
      "webp_qf": [
        75
      ]
    }
  ],
  "jobs": [],
  "schools": [],
  "teaser": {
    "string": ""
  },
  "teasers": [],
  "gender": 1,
  "birth_date_info": "fuzzy birthdate active, not displaying real birth_date",
  "s_number": 302937713
}