{
  "group_matched": false,
  "distance_mi": 35,
  "content_hash": "9MquQqubSn7IQECqC81sYrsp5S27twbHnYt5cDvcgYCJ5",
  "common_friends": [],
  "common_likes": [],
  "common_friend_count": 0,
  "common_like_count": 0,
  "connection_count": 0,
  "_id": "5be49c768452850f27f917d1",
  "bio": "",
  "birth_date": "1998-11-24T14:15:53.282Z",
  "name": "Jacinta",
  "ping_time": "2014-12-09T00:00:00.000Z",
  "photos": [
    {
      "id": "a48605f1-2e12-4e3a-8bbe-5cb00bd7dbe8",
      "crop_info": {
        "user": {
          "width_pct": 1,
          "x_offset_pct": 0,
          "height_pct": 0.8,
          "y_offset_pct": 0
        },
        "algo": {
          "width_pct": 0.11354946091305462,
          "x_offset_pct": 0.5074938090983778,
          "height_pct": 0.11958668849430978,
          "y_offset_pct": 0.16040641880594195
        },
        "processed_by_bullseye": true,
        "user_customized": false
      },
      "url": "https://images-ssl.gotinder.com/5be49c768452850f27f917d1/original_a48605f1-2e12-4e3a-8bbe-5cb00bd7dbe8.jpeg",
      "processedFiles": [
        {
          "url": "https://images-ssl.gotinder.com/5be49c768452850f27f917d1/640x800_a48605f1-2e12-4e3a-8bbe-5cb00bd7dbe8.jpg",
          "height": 800,
          "width": 640
        },
        {
          "url": "https://images-ssl.gotinder.com/5be49c768452850f27f917d1/320x400_a48605f1-2e12-4e3a-8bbe-5cb00bd7dbe8.jpg",
          "height": 400,
          "width": 320
        },
        {
          "url": "https://images-ssl.gotinder.com/5be49c768452850f27f917d1/172x216_a48605f1-2e12-4e3a-8bbe-5cb00bd7dbe8.jpg",
          "height": 216,
          "width": 172
        },
        {
          "url": "https://images-ssl.gotinder.com/5be49c768452850f27f917d1/84x106_a48605f1-2e12-4e3a-8bbe-5cb00bd7dbe8.jpg",
          "height": 106,
          "width": 84
        }
      ],
      "last_update_time": "2019-11-04T18:59:54.369Z",
      "fileName": "a48605f1-2e12-4e3a-8bbe-5cb00bd7dbe8.webp",
      "extension": "jpg,webp",
      "webp_qf": [
        75
      ]
    },
    {
      "id": "e58ada17-54ab-42cc-a5bc-dd6032633119",
      "crop_info": {
        "user": {
          "width_pct": 1,
          "x_offset_pct": 0,
          "height_pct": 0.8,
          "y_offset_pct": 0
        },
        "algo": {
          "width_pct": 0.19781166074099021,
          "x_offset_pct": 0.29721588123356923,
          "height_pct": 0.23176554863806817,
          "y_offset_pct": 0.16862516848370432
        },
        "processed_by_bullseye": true,
        "user_customized": false
      },
      "url": "https://images-ssl.gotinder.com/5be49c768452850f27f917d1/original_e58ada17-54ab-42cc-a5bc-dd6032633119.jpeg",
      "processedFiles": [
        {
          "url": "https://images-ssl.gotinder.com/5be49c768452850f27f917d1/640x800_e58ada17-54ab-42cc-a5bc-dd6032633119.jpg",
          "height": 800,
          "width": 640
        },
        {
          "url": "https://images-ssl.gotinder.com/5be49c768452850f27f917d1/320x400_e58ada17-54ab-42cc-a5bc-dd6032633119.jpg",
          "height": 400,
          "width": 320
        },
        {
          "url": "https://images-ssl.gotinder.com/5be49c768452850f27f917d1/172x216_e58ada17-54ab-42cc-a5bc-dd6032633119.jpg",
          "height": 216,
          "width": 172
        },
        {
          "url": "https://images-ssl.gotinder.com/5be49c768452850f27f917d1/84x106_e58ada17-54ab-42cc-a5bc-dd6032633119.jpg",
          "height": 106,
          "width": 84
        }
      ],
      "last_update_time": "2019-11-09T18:50:49.116Z",
      "fileName": "e58ada17-54ab-42cc-a5bc-dd6032633119.webp",
      "extension": "jpg,webp",
      "webp_qf": [
        75
      ]
    },
    {
      "id": "2812f997-ced9-47b3-93fd-c55f90c2c05f",
      "crop_info": {
        "user": {
          "width_pct": 1,
          "x_offset_pct": 0,
          "height_pct": 0.8,
          "y_offset_pct": 0
        },
        "algo": {
          "width_pct": 0.09527425074484203,
          "x_offset_pct": 0.4503316033631563,
          "height_pct": 0.11488777179270984,
          "y_offset_pct": 0.1969715392589569
        },
        "processed_by_bullseye": true,
        "user_customized": false
      },
      "url": "https://images-ssl.gotinder.com/5be49c768452850f27f917d1/original_2812f997-ced9-47b3-93fd-c55f90c2c05f.jpeg",
      "processedFiles": [
        {
          "url": "https://images-ssl.gotinder.com/5be49c768452850f27f917d1/640x800_2812f997-ced9-47b3-93fd-c55f90c2c05f.jpg",
          "height": 800,
          "width": 640
        },
        {
          "url": "https://images-ssl.gotinder.com/5be49c768452850f27f917d1/320x400_2812f997-ced9-47b3-93fd-c55f90c2c05f.jpg",
          "height": 400,
          "width": 320
        },
        {
          "url": "https://images-ssl.gotinder.com/5be49c768452850f27f917d1/172x216_2812f997-ced9-47b3-93fd-c55f90c2c05f.jpg",
          "height": 216,
          "width": 172
        },
        {
          "url": "https://images-ssl.gotinder.com/5be49c768452850f27f917d1/84x106_2812f997-ced9-47b3-93fd-c55f90c2c05f.jpg",
          "height": 106,
          "width": 84
        }
      ],
      "last_update_time": "2019-11-04T18:59:02.961Z",
      "fileName": "2812f997-ced9-47b3-93fd-c55f90c2c05f.webp",
      "extension": "jpg,webp",
      "webp_qf": [
        75
      ]
    },
    {
      "id": "d109ce40-6a2b-479e-98fa-606856c54fd3",
      "crop_info": {
        "user": {
          "width_pct": 1,
          "x_offset_pct": 0,
          "height_pct": 0.8,
          "y_offset_pct": 0
        },
        "algo": {
          "width_pct": 0.10977591422852129,
          "x_offset_pct": 0.3913918923586607,
          "height_pct": 0.11570606632158162,
          "y_offset_pct": 0.19369659151881932
        },
        "processed_by_bullseye": true,
        "user_customized": false
      },
      "url": "https://images-ssl.gotinder.com/5be49c768452850f27f917d1/original_d109ce40-6a2b-479e-98fa-606856c54fd3.jpeg",
      "processedFiles": [
        {
          "url": "https://images-ssl.gotinder.com/5be49c768452850f27f917d1/640x800_d109ce40-6a2b-479e-98fa-606856c54fd3.jpg",
          "height": 800,
          "width": 640
        },
        {
          "url": "https://images-ssl.gotinder.com/5be49c768452850f27f917d1/320x400_d109ce40-6a2b-479e-98fa-606856c54fd3.jpg",
          "height": 400,
          "width": 320
        },
        {
          "url": "https://images-ssl.gotinder.com/5be49c768452850f27f917d1/172x216_d109ce40-6a2b-479e-98fa-606856c54fd3.jpg",
          "height": 216,
          "width": 172
        },
        {
          "url": "https://images-ssl.gotinder.com/5be49c768452850f27f917d1/84x106_d109ce40-6a2b-479e-98fa-606856c54fd3.jpg",
          "height": 106,
          "width": 84
        }
      ],
      "last_update_time": "2019-11-17T10:16:17.792Z",
      "fileName": "d109ce40-6a2b-479e-98fa-606856c54fd3.webp",
      "extension": "jpg,webp",
      "webp_qf": [
        75
      ]
    }
  ],
  "jobs": [
    {
      "title": {
        "name": "Friseurin"
      }
    }
  ],
  "schools": [],
  "teaser": {
    "type": "job",
    "string": "Friseurin"
  },
  "teasers": [
    {
      "type": "job",
      "string": "Friseurin"
    }
  ],
  "gender": 1,
  "birth_date_info": "fuzzy birthdate active, not displaying real birth_date",
  "s_number": 647522217
}