{
  "group_matched": false,
  "distance_mi": 91,
  "content_hash": "DYksLqfblswZClNf7diQlTw8TpkijJiVvT0AULPTDdI8GSYl",
  "common_friends": [],
  "common_likes": [],
  "common_friend_count": 0,
  "common_like_count": 0,
  "connection_count": 0,
  "_id": "5cf4d3037074791500e67214",
  "bio": "[insert interesting words here]",
  "birth_date": "2000-11-25T20:11:09.690Z",
  "name": "Jill",
  "ping_time": "2014-12-09T00:00:00.000Z",
  "photos": [
    {
      "id": "eca6828c-605e-4df5-b63e-75a95f52c9c4",
      "crop_info": {
        "user": {
          "width_pct": 1,
          "x_offset_pct": 0,
          "height_pct": 0.8,
          "y_offset_pct": 0
        },
        "algo": {
          "width_pct": 0.15952189749805257,
          "x_offset_pct": 0.33062726989155633,
          "height_pct": 0.1582369640143588,
          "y_offset_pct": 0.230203026519157
        },
        "processed_by_bullseye": true,
        "user_customized": false
      },
      "url": "https://images-ssl.gotinder.com/5cf4d3037074791500e67214/original_eca6828c-605e-4df5-b63e-75a95f52c9c4.jpeg",
      "processedFiles": [
        {
          "url": "https://images-ssl.gotinder.com/5cf4d3037074791500e67214/640x800_eca6828c-605e-4df5-b63e-75a95f52c9c4.jpg",
          "height": 800,
          "width": 640
        },
        {
          "url": "https://images-ssl.gotinder.com/5cf4d3037074791500e67214/320x400_eca6828c-605e-4df5-b63e-75a95f52c9c4.jpg",
          "height": 400,
          "width": 320
        },
        {
          "url": "https://images-ssl.gotinder.com/5cf4d3037074791500e67214/172x216_eca6828c-605e-4df5-b63e-75a95f52c9c4.jpg",
          "height": 216,
          "width": 172
        },
        {
          "url": "https://images-ssl.gotinder.com/5cf4d3037074791500e67214/84x106_eca6828c-605e-4df5-b63e-75a95f52c9c4.jpg",
          "height": 106,
          "width": 84
        }
      ],
      "last_update_time": "2019-10-13T18:03:22.665Z",
      "fileName": "eca6828c-605e-4df5-b63e-75a95f52c9c4.webp",
      "extension": "jpg,webp",
      "webp_qf": [
        75
      ]
    },
    {
      "id": "f705bbdb-621c-4fb1-bbf9-8b4e4a23250b",
      "crop_info": {
        "processed_by_bullseye": true,
        "user_customized": false
      },
      "url": "https://images-ssl.gotinder.com/5cf4d3037074791500e67214/original_f705bbdb-621c-4fb1-bbf9-8b4e4a23250b.jpeg",
      "processedFiles": [
        {
          "url": "https://images-ssl.gotinder.com/5cf4d3037074791500e67214/640x800_f705bbdb-621c-4fb1-bbf9-8b4e4a23250b.jpg",
          "height": 800,
          "width": 640
        },
        {
          "url": "https://images-ssl.gotinder.com/5cf4d3037074791500e67214/320x400_f705bbdb-621c-4fb1-bbf9-8b4e4a23250b.jpg",
          "height": 400,
          "width": 320
        },
        {
          "url": "https://images-ssl.gotinder.com/5cf4d3037074791500e67214/172x216_f705bbdb-621c-4fb1-bbf9-8b4e4a23250b.jpg",
          "height": 216,
          "width": 172
        },
        {
          "url": "https://images-ssl.gotinder.com/5cf4d3037074791500e67214/84x106_f705bbdb-621c-4fb1-bbf9-8b4e4a23250b.jpg",
          "height": 106,
          "width": 84
        }
      ],
      "last_update_time": "2019-10-13T18:05:07.222Z",
      "fileName": "f705bbdb-621c-4fb1-bbf9-8b4e4a23250b.webp",
      "extension": "jpg,webp",
      "webp_qf": [
        75
      ]
    },
    {
      "id": "775b071c-4150-4df0-ae36-35e572d6f0e8",
      "crop_info": {
        "processed_by_bullseye": true,
        "user_customized": false
      },
      "url": "https://images-ssl.gotinder.com/5cf4d3037074791500e67214/original_775b071c-4150-4df0-ae36-35e572d6f0e8.jpeg",
      "processedFiles": [
        {
          "url": "https://images-ssl.gotinder.com/5cf4d3037074791500e67214/640x800_775b071c-4150-4df0-ae36-35e572d6f0e8.jpg",
          "height": 800,
          "width": 640
        },
        {
          "url": "https://images-ssl.gotinder.com/5cf4d3037074791500e67214/320x400_775b071c-4150-4df0-ae36-35e572d6f0e8.jpg",
          "height": 400,
          "width": 320
        },
        {
          "url": "https://images-ssl.gotinder.com/5cf4d3037074791500e67214/172x216_775b071c-4150-4df0-ae36-35e572d6f0e8.jpg",
          "height": 216,
          "width": 172
        },
        {
          "url": "https://images-ssl.gotinder.com/5cf4d3037074791500e67214/84x106_775b071c-4150-4df0-ae36-35e572d6f0e8.jpg",
          "height": 106,
          "width": 84
        }
      ],
      "last_update_time": "2019-10-31T17:37:46.345Z",
      "fileName": "775b071c-4150-4df0-ae36-35e572d6f0e8.webp",
      "extension": "jpg,webp",
      "webp_qf": [
        75
      ]
    },
    {
      "id": "502fae29-8dbf-4845-b7f4-f5a1fb36f2f9",
      "crop_info": {
        "processed_by_bullseye": true,
        "user_customized": false
      },
      "url": "https://images-ssl.gotinder.com/5cf4d3037074791500e67214/original_502fae29-8dbf-4845-b7f4-f5a1fb36f2f9.jpeg",
      "processedFiles": [
        {
          "url": "https://images-ssl.gotinder.com/5cf4d3037074791500e67214/640x800_502fae29-8dbf-4845-b7f4-f5a1fb36f2f9.jpg",
          "height": 800,
          "width": 640
        },
        {
          "url": "https://images-ssl.gotinder.com/5cf4d3037074791500e67214/320x400_502fae29-8dbf-4845-b7f4-f5a1fb36f2f9.jpg",
          "height": 400,
          "width": 320
        },
        {
          "url": "https://images-ssl.gotinder.com/5cf4d3037074791500e67214/172x216_502fae29-8dbf-4845-b7f4-f5a1fb36f2f9.jpg",
          "height": 216,
          "width": 172
        },
        {
          "url": "https://images-ssl.gotinder.com/5cf4d3037074791500e67214/84x106_502fae29-8dbf-4845-b7f4-f5a1fb36f2f9.jpg",
          "height": 106,
          "width": 84
        }
      ],
      "last_update_time": "2019-10-31T17:37:47.428Z",
      "fileName": "502fae29-8dbf-4845-b7f4-f5a1fb36f2f9.webp",
      "extension": "jpg,webp",
      "webp_qf": [
        75
      ]
    }
  ],
  "jobs": [],
  "schools": [],
  "teaser": {
    "string": ""
  },
  "teasers": [],
  "gender": 1,
  "birth_date_info": "fuzzy birthdate active, not displaying real birth_date",
  "s_number": 755680740
}