{
  "group_matched": false,
  "distance_mi": 56,
  "content_hash": "mv7HoRflUgjUNohLSmvUD7H2Oie6inZupVfE1s6zfgHm5",
  "common_friends": [],
  "common_likes": [],
  "common_friend_count": 0,
  "common_like_count": 0,
  "connection_count": 0,
  "_id": "5ddfe078ac6e6f01004f79e3",
  "bio": "🇯🇵✈︎🇩🇪\nEnglish und ein bisschen Deutsch🐈",
  "birth_date": "1997-12-01T16:02:39.719Z",
  "name": "Rika",
  "ping_time": "2014-12-09T00:00:00.000Z",
  "photos": [
    {
      "id": "b68a099d-5205-41d6-88e2-d64499ae24ea",
      "crop_info": {
        "user": {
          "width_pct": 1,
          "x_offset_pct": 0,
          "height_pct": 0.8,
          "y_offset_pct": 0
        },
        "algo": {
          "width_pct": 0.12264963544439522,
          "x_offset_pct": 0.4446846804348752,
          "height_pct": 0.12301174445543436,
          "y_offset_pct": 0.2248232104210183
        },
        "processed_by_bullseye": true,
        "user_customized": false
      },
      "url": "https://images-ssl.gotinder.com/5ddfe078ac6e6f01004f79e3/original_b68a099d-5205-41d6-88e2-d64499ae24ea.jpeg",
      "processedFiles": [
        {
          "url": "https://images-ssl.gotinder.com/5ddfe078ac6e6f01004f79e3/640x800_b68a099d-5205-41d6-88e2-d64499ae24ea.jpg",
          "height": 800,
          "width": 640
        },
        {
          "url": "https://images-ssl.gotinder.com/5ddfe078ac6e6f01004f79e3/320x400_b68a099d-5205-41d6-88e2-d64499ae24ea.jpg",
          "height": 400,
          "width": 320
        },
        {
          "url": "https://images-ssl.gotinder.com/5ddfe078ac6e6f01004f79e3/172x216_b68a099d-5205-41d6-88e2-d64499ae24ea.jpg",
          "height": 216,
          "width": 172
        },
        {
          "url": "https://images-ssl.gotinder.com/5ddfe078ac6e6f01004f79e3/84x106_b68a099d-5205-41d6-88e2-d64499ae24ea.jpg",
          "height": 106,
          "width": 84
        }
      ],
      "last_update_time": "2019-11-28T14:57:59.572Z",
      "fileName": "b68a099d-5205-41d6-88e2-d64499ae24ea.webp",
      "extension": "jpg,webp",
      "webp_qf": [
        75
      ]
    },
    {
      "id": "c54486ca-865a-42d6-b398-ac415b0ba2e8",
      "crop_info": {
        "processed_by_bullseye": true,
        "user_customized": false
      },
      "url": "https://images-ssl.gotinder.com/5ddfe078ac6e6f01004f79e3/original_c54486ca-865a-42d6-b398-ac415b0ba2e8.jpeg",
      "processedFiles": [
        {
          "url": "https://images-ssl.gotinder.com/5ddfe078ac6e6f01004f79e3/640x800_c54486ca-865a-42d6-b398-ac415b0ba2e8.jpg",
          "height": 800,
          "width": 640
        },
        {
          "url": "https://images-ssl.gotinder.com/5ddfe078ac6e6f01004f79e3/320x400_c54486ca-865a-42d6-b398-ac415b0ba2e8.jpg",
          "height": 400,
          "width": 320
        },
        {
          "url": "https://images-ssl.gotinder.com/5ddfe078ac6e6f01004f79e3/172x216_c54486ca-865a-42d6-b398-ac415b0ba2e8.jpg",
          "height": 216,
          "width": 172
        },
        {
          "url": "https://images-ssl.gotinder.com/5ddfe078ac6e6f01004f79e3/84x106_c54486ca-865a-42d6-b398-ac415b0ba2e8.jpg",
          "height": 106,
          "width": 84
        }
      ],
      "last_update_time": "2019-11-28T15:14:37.214Z",
      "fileName": "c54486ca-865a-42d6-b398-ac415b0ba2e8.webp",
      "extension": "jpg,webp",
      "webp_qf": [
        75
      ]
    },
    {
      "id": "bae1c293-a56c-40b3-a0ba-c59693bbf192",
      "crop_info": {
        "user": {
          "width_pct": 1,
          "x_offset_pct": 0,
          "height_pct": 0.8,
          "y_offset_pct": 0
        },
        "algo": {
          "width_pct": 0.08775399313308302,
          "x_offset_pct": 0.47395738093182443,
          "height_pct": 0.08359730673953894,
          "y_offset_pct": 0.23550615794956684
        },
        "processed_by_bullseye": true,
        "user_customized": false
      },
      "url": "https://images-ssl.gotinder.com/5ddfe078ac6e6f01004f79e3/original_bae1c293-a56c-40b3-a0ba-c59693bbf192.jpeg",
      "processedFiles": [
        {
          "url": "https://images-ssl.gotinder.com/5ddfe078ac6e6f01004f79e3/640x800_bae1c293-a56c-40b3-a0ba-c59693bbf192.jpg",
          "height": 800,
          "width": 640
        },
        {
          "url": "https://images-ssl.gotinder.com/5ddfe078ac6e6f01004f79e3/320x400_bae1c293-a56c-40b3-a0ba-c59693bbf192.jpg",
          "height": 400,
          "width": 320
        },
        {
          "url": "https://images-ssl.gotinder.com/5ddfe078ac6e6f01004f79e3/172x216_bae1c293-a56c-40b3-a0ba-c59693bbf192.jpg",
          "height": 216,
          "width": 172
        },
        {
          "url": "https://images-ssl.gotinder.com/5ddfe078ac6e6f01004f79e3/84x106_bae1c293-a56c-40b3-a0ba-c59693bbf192.jpg",
          "height": 106,
          "width": 84
        }
      ],
      "last_update_time": "2019-11-28T15:28:12.685Z",
      "fileName": "bae1c293-a56c-40b3-a0ba-c59693bbf192.webp",
      "extension": "jpg,webp",
      "webp_qf": [
        75
      ]
    }
  ],
  "jobs": [
    {
      "title": {
        "name": "Studentin"
      }
    }
  ],
  "schools": [],
  "teaser": {
    "type": "job",
    "string": "Studentin"
  },
  "teasers": [
    {
      "type": "job",
      "string": "Studentin"
    }
  ],
  "gender": 1,
  "birth_date_info": "fuzzy birthdate active, not displaying real birth_date",
  "s_number": 853625875,
  "show_gender_on_profile": false
}