{
  "group_matched": false,
  "distance_mi": 6,
  "content_hash": "YeU25SNpua0Sa4TOaCmzhm5HG0Uwni88FVqibHQpUpNcZq",
  "common_friends": [],
  "common_likes": [],
  "common_friend_count": 0,
  "common_like_count": 0,
  "connection_count": 0,
  "_id": "5d7e605c53e04bc9692b14d6",
  "bio": "instagram: darlene_mglhs \ngerman/portuguese\n\n💃🏽🍷",
  "birth_date": "1993-11-21T22:15:13.230Z",
  "name": "Darlene",
  "ping_time": "2014-12-09T00:00:00.000Z",
  "photos": [
    {
      "id": "259eb83d-c0ba-46d0-b594-87d6084f5f45",
      "crop_info": {
        "user": {
          "width_pct": 1,
          "x_offset_pct": 0,
          "height_pct": 0.8,
          "y_offset_pct": 0
        },
        "algo": {
          "width_pct": 0.37466021366417407,
          "x_offset_pct": 0.20354667976498603,
          "height_pct": 0.31194248296320437,
          "y_offset_pct": 0.10057353146374226
        },
        "processed_by_bullseye": true,
        "user_customized": false
      },
      "url": "https://images-ssl.gotinder.com/5d7e605c53e04bc9692b14d6/original_259eb83d-c0ba-46d0-b594-87d6084f5f45.jpeg",
      "processedFiles": [
        {
          "url": "https://images-ssl.gotinder.com/5d7e605c53e04bc9692b14d6/640x800_259eb83d-c0ba-46d0-b594-87d6084f5f45.jpg",
          "height": 800,
          "width": 640
        },
        {
          "url": "https://images-ssl.gotinder.com/5d7e605c53e04bc9692b14d6/320x400_259eb83d-c0ba-46d0-b594-87d6084f5f45.jpg",
          "height": 400,
          "width": 320
        },
        {
          "url": "https://images-ssl.gotinder.com/5d7e605c53e04bc9692b14d6/172x216_259eb83d-c0ba-46d0-b594-87d6084f5f45.jpg",
          "height": 216,
          "width": 172
        },
        {
          "url": "https://images-ssl.gotinder.com/5d7e605c53e04bc9692b14d6/84x106_259eb83d-c0ba-46d0-b594-87d6084f5f45.jpg",
          "height": 106,
          "width": 84
        }
      ],
      "last_update_time": "2019-09-15T16:21:43.814Z",
      "fileName": "259eb83d-c0ba-46d0-b594-87d6084f5f45.webp",
      "extension": "jpg,webp",
      "webp_qf": [
        75
      ]
    },
    {
      "id": "9bdd02ea-61c2-4d84-8f03-71e183e4706b",
      "crop_info": {
        "user": {
          "width_pct": 1,
          "x_offset_pct": 0,
          "height_pct": 0.8,
          "y_offset_pct": 0
        },
        "algo": {
          "width_pct": 0.4719404787290842,
          "x_offset_pct": 0.2515445569530129,
          "height_pct": 0.5244006052799522,
          "y_offset_pct": 0.11420118644833564
        },
        "processed_by_bullseye": true,
        "user_customized": false
      },
      "url": "https://images-ssl.gotinder.com/5d7e605c53e04bc9692b14d6/original_9bdd02ea-61c2-4d84-8f03-71e183e4706b.jpeg",
      "processedFiles": [
        {
          "url": "https://images-ssl.gotinder.com/5d7e605c53e04bc9692b14d6/640x800_9bdd02ea-61c2-4d84-8f03-71e183e4706b.jpg",
          "height": 800,
          "width": 640
        },
        {
          "url": "https://images-ssl.gotinder.com/5d7e605c53e04bc9692b14d6/320x400_9bdd02ea-61c2-4d84-8f03-71e183e4706b.jpg",
          "height": 400,
          "width": 320
        },
        {
          "url": "https://images-ssl.gotinder.com/5d7e605c53e04bc9692b14d6/172x216_9bdd02ea-61c2-4d84-8f03-71e183e4706b.jpg",
          "height": 216,
          "width": 172
        },
        {
          "url": "https://images-ssl.gotinder.com/5d7e605c53e04bc9692b14d6/84x106_9bdd02ea-61c2-4d84-8f03-71e183e4706b.jpg",
          "height": 106,
          "width": 84
        }
      ],
      "last_update_time": "2019-09-16T06:58:45.009Z",
      "fileName": "9bdd02ea-61c2-4d84-8f03-71e183e4706b.webp",
      "extension": "jpg,webp",
      "webp_qf": [
        75
      ]
    }
  ],
  "jobs": [],
  "schools": [],
  "teaser": {
    "string": ""
  },
  "teasers": [],
  "gender": 1,
  "birth_date_info": "fuzzy birthdate active, not displaying real birth_date",
  "s_number": 806062999,
  "show_gender_on_profile": false
}