{
  "group_matched": false,
  "distance_mi": 17,
  "content_hash": "E2lUOIlvibEt0Af3qFgwhpnFjaFAaTMXSe3HNvSY9IvwSYQ",
  "common_friends": [],
  "common_likes": [],
  "common_friend_count": 0,
  "common_like_count": 0,
  "connection_count": 0,
  "_id": "5df1195149bff20100e92c57",
  "bio": "",
  "birth_date": "1993-12-15T10:02:15.024Z",
  "name": "Joanna",
  "ping_time": "2014-12-09T00:00:00.000Z",
  "photos": [
    {
      "id": "ed1d9e37-748f-46ff-ad31-cf4e2fad3d55",
      "crop_info": {
        "user": {
          "width_pct": 1,
          "x_offset_pct": 0,
          "height_pct": 0.8,
          "y_offset_pct": 0
        },
        "algo": {
          "width_pct": 0.44457519277930263,
          "x_offset_pct": 0.33709628991782664,
          "height_pct": 0.48026072467677294,
          "y_offset_pct": 0.014548554606735707
        },
        "processed_by_bullseye": true,
        "user_customized": false
      },
      "url": "https://images-ssl.gotinder.com/5df1195149bff20100e92c57/original_ed1d9e37-748f-46ff-ad31-cf4e2fad3d55.jpeg",
      "processedFiles": [
        {
          "url": "https://images-ssl.gotinder.com/5df1195149bff20100e92c57/640x800_ed1d9e37-748f-46ff-ad31-cf4e2fad3d55.jpg",
          "height": 800,
          "width": 640
        },
        {
          "url": "https://images-ssl.gotinder.com/5df1195149bff20100e92c57/320x400_ed1d9e37-748f-46ff-ad31-cf4e2fad3d55.jpg",
          "height": 400,
          "width": 320
        },
        {
          "url": "https://images-ssl.gotinder.com/5df1195149bff20100e92c57/172x216_ed1d9e37-748f-46ff-ad31-cf4e2fad3d55.jpg",
          "height": 216,
          "width": 172
        },
        {
          "url": "https://images-ssl.gotinder.com/5df1195149bff20100e92c57/84x106_ed1d9e37-748f-46ff-ad31-cf4e2fad3d55.jpg",
          "height": 106,
          "width": 84
        }
      ],
      "last_update_time": "2019-12-11T16:29:52.440Z",
      "fileName": "ed1d9e37-748f-46ff-ad31-cf4e2fad3d55.webp",
      "extension": "jpg,webp",
      "main": true,
      "webp_qf": [
        75
      ]
    }
  ],
  "jobs": [],
  "schools": [],
  "teaser": {
    "string": ""
  },
  "teasers": [],
  "gender": 1,
  "birth_date_info": "fuzzy birthdate active, not displaying real birth_date",
  "s_number": 860374358,
  "show_gender_on_profile": false
}