{
  "group_matched": false,
  "distance_mi": 99,
  "content_hash": "v9NhMt0pilfgMiOGUVkFolIk1Fq2H2wTaVcndsAlUj0Uwg",
  "common_friends": [],
  "common_likes": [],
  "common_friend_count": 0,
  "common_like_count": 0,
  "connection_count": 0,
  "_id": "5d2c6237743e0a2000e5a437",
  "bio": "Festival- Harder Styles 🎡🎼\nReisen 🌞🏝\nDog 🐶",
  "birth_date": "1992-11-25T20:11:41.528Z",
  "name": "Melli",
  "ping_time": "2014-12-09T00:00:00.000Z",
  "photos": [
    {
      "id": "710d860c-3e5d-49bd-84c8-51f1d081419d",
      "crop_info": {
        "user": {
          "width_pct": 1,
          "x_offset_pct": 0,
          "height_pct": 1,
          "y_offset_pct": 0
        },
        "algo": {
          "width_pct": 0.5195068876026198,
          "x_offset_pct": 0.1281587707111612,
          "height_pct": 0.6724201191915199,
          "y_offset_pct": 0.06815893454477191
        },
        "processed_by_bullseye": true,
        "user_customized": false
      },
      "url": "https://images-ssl.gotinder.com/5d2c6237743e0a2000e5a437/original_710d860c-3e5d-49bd-84c8-51f1d081419d.jpeg",
      "processedFiles": [
        {
          "url": "https://images-ssl.gotinder.com/5d2c6237743e0a2000e5a437/640x640_710d860c-3e5d-49bd-84c8-51f1d081419d.jpg",
          "height": 640,
          "width": 640
        },
        {
          "url": "https://images-ssl.gotinder.com/5d2c6237743e0a2000e5a437/320x320_710d860c-3e5d-49bd-84c8-51f1d081419d.jpg",
          "height": 320,
          "width": 320
        },
        {
          "url": "https://images-ssl.gotinder.com/5d2c6237743e0a2000e5a437/172x172_710d860c-3e5d-49bd-84c8-51f1d081419d.jpg",
          "height": 172,
          "width": 172
        },
        {
          "url": "https://images-ssl.gotinder.com/5d2c6237743e0a2000e5a437/84x84_710d860c-3e5d-49bd-84c8-51f1d081419d.jpg",
          "height": 84,
          "width": 84
        }
      ],
      "last_update_time": "2019-07-15T11:23:34.845Z",
      "fileName": "710d860c-3e5d-49bd-84c8-51f1d081419d.webp",
      "extension": "jpg,webp",
      "webp_qf": [
        75
      ]
    }
  ],
  "jobs": [
    {
      "title": {
        "name": "Krankenschwester"
      }
    }
  ],
  "schools": [],
  "teaser": {
    "type": "job",
    "string": "Krankenschwester"
  },
  "teasers": [
    {
      "type": "job",
      "string": "Krankenschwester"
    }
  ],
  "gender": 1,
  "birth_date_info": "fuzzy birthdate active, not displaying real birth_date",
  "s_number": 778289928,
  "spotify_theme_track": {
    "id": "1DhRbox3xkceP64k3JeYfW",
    "name": "Antisocial (with Travis Scott)",
    "album": {
      "id": "3oIFxDIo2fwuk4lwCmFZCx",
      "name": "No.6 Collaborations Project",
      "images": [
        {
          "height": 640,
          "width": 640,
          "url": "https://i.scdn.co/image/4b516036a8449204a10703afa350331c57bf694c"
        },
        {
          "height": 300,
          "width": 300,
          "url": "https://i.scdn.co/image/9bf3cb023bb55171a2c974e998325a15a17113d4"
        },
        {
          "height": 64,
          "width": 64,
          "url": "https://i.scdn.co/image/fd4ef7987cbdd81124b1de291838282a03f05f9f"
        }
      ]
    },
    "artists": [
      {
        "id": "6eUKZXaKkcviH0Ku9w2n3V",
        "name": "Ed Sheeran"
      },
      {
        "id": "0Y5tJX1MQlPlqiwlOH1tJY",
        "name": "Travis Scott"
      }
    ],
    "preview_url": "https://p.scdn.co/mp3-preview/465e03abf0eaf729079686d297700a9feed7dab6?cid=b06a803d686e4612bdc074e786e94062",
    "uri": "spotify:track:1DhRbox3xkceP64k3JeYfW"
  },
  "show_gender_on_profile": true
}